slots_class/__init__.py
slots_class/__main__.py
slots_class/descriptor.py
slots_class/py.typed
slots_class/py_descriptor.py
slots_class/slots_class.py
slots_class/slots_class_meta.py
slots_class/_annotations/__init__.py
slots_class-0.1.0a2.dist-info/METADATA
slots_class-0.1.0a2.dist-info/WHEEL
slots_class-0.1.0a2.dist-info/licenses/LICENSE
slots_class-0.1.0a2.dist-info/RECORD
