Metadata-Version: 2.4
Name: slots-class
Version: 0.1.0a2
Summary: A modern object model that uses __slots__
Project-URL: Homepage, https://github.com/mkzeender/slots-class
Project-URL: Documentation, https://github.com/mkzeender/slots-class
Author-email: Marckie Zeender <mkzeender@gmail.com>
License-Expression: MIT
License-File: LICENSE
Keywords: __slots__,attr,attribute,class,dataclass,slots
Requires-Python: >=3.13
